statline_bq/__init__.py
statline_bq/cli.py
statline_bq/config.py
statline_bq/config.toml
statline_bq/datasets.toml
statline_bq/gcpl.py
statline_bq/log.py
statline_bq/logging_conf.toml
statline_bq/main.py
statline_bq/statline.py
statline_bq/utils.py
statline_bq-0.2.0.dist-info/entry_points.txt
statline_bq-0.2.0.dist-info/LICENSE
statline_bq-0.2.0.dist-info/WHEEL
statline_bq-0.2.0.dist-info/METADATA
statline_bq-0.2.0.dist-info/RECORD
